AUTHORS
LICENSE
MANIFEST.in
README.rst
THANKS
TODO
setup.py
restdyn/__init__.py
restdyn/client.py
restdyn.egg-info/PKG-INFO
restdyn.egg-info/SOURCES.txt
restdyn.egg-info/dependency_links.txt
restdyn.egg-info/not-zip-safe
restdyn.egg-info/requires.txt
restdyn.egg-info/top_level.txt
tests/bottle.py
tests/bottle.pyc
tests/test_client.py
tests/test_client.pyc
tests/testserver.py
tests/testserver.pyc