Metadata-Version: 1.0
Name: restdyn
Version: 0.3
Summary: A dynamic rest client
Home-page: http://github.com/namlook/restdyn
Author: Namlook
Author-email: UNKNOWN
License: New BSD License
Platform: UNKNOWN
Classifier: Development Status :: 5 - Production/Stable
Classifier: Environment :: Other Environment
Classifier: Intended Audience :: Developers
Classifier: License :: OSI Approved :: Apache Software License
Classifier: Operating System :: OS Independent
Classifier: Programming Language :: Python
Classifier: Topic :: Utilities
Classifier: Topic :: Software Development :: Libraries :: Python Modules
